m4p/__init__.py
m4p/m4_eval.py
m4p/m4_translit.py
m4p/main.py
m4p/parser.py
m4p/regionbuffer.py
m4p/stream.py
m4p-0.3.dist-info/licenses/COPYING
m4p-0.3.dist-info/METADATA
m4p-0.3.dist-info/WHEEL
m4p-0.3.dist-info/entry_points.txt
m4p-0.3.dist-info/top_level.txt
m4p-0.3.dist-info/RECORD
